im2geojson/__init__.py
im2geojson/__main__.py
im2geojson/cli.py
im2geojson/dms_conversion.py
im2geojson/exif_reader.py
im2geojson/geojson_parser.py
im2geojson/im2geojson.py
im2geojson/logging_config.py
im2geojson/timer.py
im2geojson-0.2.1.dist-info/LICENCE
im2geojson-0.2.1.dist-info/METADATA
im2geojson-0.2.1.dist-info/WHEEL
im2geojson-0.2.1.dist-info/top_level.txt
im2geojson-0.2.1.dist-info/RECORD
