Metadata-Version: 2.1
Name: im2geojson
Version: 0.2.1
Summary: GeoJSON from image metadata
Author-email: Michael Bishop <mbishop@tutanota.com>
Project-URL: Homepage, https://pypi.org/project/im2geojson/
Project-URL: Documentation, https://mjbishop.github.io/im2geojson/im2geojson.html
Project-URL: Repository, https://github.com/MJBishop/im2geojson
Keywords: GeoJSON,Image,GPS metadata
Classifier: Development Status :: 5 - Production/Stable
Classifier: Intended Audience :: Developers
Classifier: Programming Language :: Python :: 3
Classifier: License :: OSI Approved :: MIT License
Classifier: Operating System :: OS Independent
Requires-Python: >=3.8
License-File: LICENCE
Requires-Dist: exif>=1.6.0
Requires-Dist: geojson>=3.1.0
